concurry/__init__.py
concurry/config.py
concurry/executor.py
concurry/core/__init__.py
concurry/core/constants.py
concurry/core/future.py
concurry/core/retry.py
concurry/core/synch.py
concurry/core/algorithms/__init__.py
concurry/core/algorithms/load_balancing.py
concurry/core/algorithms/polling.py
concurry/core/algorithms/rate_limiting.py
concurry/core/limit/__init__.py
concurry/core/limit/acquisition.py
concurry/core/limit/limit.py
concurry/core/limit/limit_pool.py
concurry/core/limit/limit_set.py
concurry/core/worker/__init__.py
concurry/core/worker/asyncio_worker.py
concurry/core/worker/base_worker.py
concurry/core/worker/process_worker.py
concurry/core/worker/ray_worker.py
concurry/core/worker/sync_worker.py
concurry/core/worker/task_decorator.py
concurry/core/worker/task_worker.py
concurry/core/worker/thread_worker.py
concurry/core/worker/worker_pool.py
concurry/utils/__init__.py
concurry/utils/environment.py
concurry/utils/frameworks.py
concurry/utils/progress.py
concurry/utils/timer.py
concurry-0.12.2.dist-info/METADATA
concurry-0.12.2.dist-info/WHEEL
concurry-0.12.2.dist-info/licenses/LICENSE
concurry-0.12.2.dist-info/RECORD
