Metadata-Version: 2.4
Name: concurry
Version: 0.12.2
Summary: A unified, delightful Python concurrency library
Author-email: Abhishek Divekar <adivekar@utexas.edu>
License-File: LICENSE
Keywords: async,concurrency,multiprocessing,parallel,ray,threading
Classifier: Development Status :: 3 - Alpha
Classifier: Intended Audience :: Developers
Classifier: License :: OSI Approved :: Apache Software License
Classifier: Operating System :: OS Independent
Classifier: Programming Language :: Python :: 3
Classifier: Programming Language :: Python :: 3.10
Classifier: Programming Language :: Python :: 3.11
Classifier: Programming Language :: Python :: 3.12
Classifier: Programming Language :: Python :: 3.13
Classifier: Topic :: Software Development :: Libraries :: Python Modules
Classifier: Topic :: System :: Distributed Computing
Requires-Python: >=3.10
Requires-Dist: cloudpickle>=2.0.0
Requires-Dist: morphic
Requires-Dist: tqdm>=4.60.0
Provides-Extra: all
Requires-Dist: aiofiles>=25.0; extra == 'all'
Requires-Dist: aiohttp>=3.13; extra == 'all'
Requires-Dist: black>=21.0; extra == 'all'
Requires-Dist: cloudpickle>=2.0.0; extra == 'all'
Requires-Dist: flake8>=3.8; extra == 'all'
Requires-Dist: mike>=2.0.0; extra == 'all'
Requires-Dist: mkdocs-material>=9.5.0; extra == 'all'
Requires-Dist: mkdocs>=1.6.0; extra == 'all'
Requires-Dist: mkdocstrings[python]>=0.24.0; extra == 'all'
Requires-Dist: morphic[all]; extra == 'all'
Requires-Dist: mypy>=0.900; extra == 'all'
Requires-Dist: pytest-asyncio>=0.21.0; extra == 'all'
Requires-Dist: pytest-cov>=2.0; extra == 'all'
Requires-Dist: pytest-sugar>=1.1.1; extra == 'all'
Requires-Dist: pytest-timeout>=2.0; extra == 'all'
Requires-Dist: pytest>=6.0; extra == 'all'
Requires-Dist: ray>=2.0.0; extra == 'all'
Requires-Dist: ray[client]; extra == 'all'
Provides-Extra: dev
Requires-Dist: aiofiles>=25.0; extra == 'dev'
Requires-Dist: aiohttp>=3.13; extra == 'dev'
Requires-Dist: black>=21.0; extra == 'dev'
Requires-Dist: flake8>=3.8; extra == 'dev'
Requires-Dist: mypy>=0.900; extra == 'dev'
Requires-Dist: pytest-asyncio>=0.21.0; extra == 'dev'
Requires-Dist: pytest-cov>=2.0; extra == 'dev'
Requires-Dist: pytest-sugar>=1.1.1; extra == 'dev'
Requires-Dist: pytest-timeout>=2.0; extra == 'dev'
Requires-Dist: pytest>=6.0; extra == 'dev'
Provides-Extra: docs
Requires-Dist: mike>=2.0.0; extra == 'docs'
Requires-Dist: mkdocs-material>=9.5.0; extra == 'docs'
Requires-Dist: mkdocs>=1.6.0; extra == 'docs'
Requires-Dist: mkdocstrings[python]>=0.24.0; extra == 'docs'
Provides-Extra: ray
Requires-Dist: cloudpickle>=2.0.0; extra == 'ray'
Requires-Dist: ray>=2.0.0; extra == 'ray'
Requires-Dist: ray[client]; extra == 'ray'
